python_sdk/__init__.py
python_sdk/__main__.py
python_sdk/__version__.py
python_sdk/py.typed
python_sdk/version
python_sdk/_cli/__init__.py
python_sdk/_cli/_cli.py
python_sdk/_cli/_fmt.py
python_sdk/_cli/_version.py
python_sdk/asyncio_atexit/__init__.py
python_sdk/asyncio_atexit/_asyncio_atexit.py
python_sdk/asyncio_atexit/_callback.py
python_sdk/asyncio_atexit/_event_loop_atexit_callback_registry.py
python_sdk/bin/__init__.py
python_sdk/bin/_call.py
python_sdk/config/__init__.py
python_sdk/config/_config.py
python_sdk/config/_config_documentation.py
python_sdk/config/_config_option.py
python_sdk/config/_config_sources.py
python_sdk/config/_config_validators.py
python_sdk/config/_config_value_types.py
python_sdk/config/_config_value_validators.py
python_sdk/config/_flags.py
python_sdk/config/_optional_type.py
python_sdk/config/_string_decoder.py
python_sdk/config/_config_source/__init__.py
python_sdk/config/_config_source/_aws_parameter_store_document.py
python_sdk/config/_config_source/_aws_secrets_manager_secret.py
python_sdk/config/_config_source/_environment_variables.py
python_sdk/config/_config_source/_factory.py
python_sdk/config/_config_source/_file_object.py
python_sdk/config/_config_source/_local_file.py
python_sdk/config/_config_source/_protocol.py
python_sdk/config/_config_source/_remote_http_file.py
python_sdk/config/_config_source/_s3_file.py
python_sdk/config/_config_source/_static_dictionary.py
python_sdk/encoding/__init__.py
python_sdk/encoding/_base64url.py
python_sdk/locks/__init__.py
python_sdk/locks/_lock_provider/__init__.py
python_sdk/locks/_lock_provider/_exceptions.py
python_sdk/locks/_lock_provider/_protocol.py
python_sdk/locks/_lock_provider/_aws_dynamodb/__init__.py
python_sdk/locks/_lock_provider/_aws_dynamodb/_aws_dynamodb.py
python_sdk/locks/_lock_provider/_s3/__init__.py
python_sdk/locks/_lock_provider/_s3/_s3.py
python_sdk/locks/_lock_provider_factory/__init__.py
python_sdk/locks/_lock_provider_factory/_aws_dynamodb_config.py
pythonsdk-0.14.0.dist-info/LICENSE
pythonsdk-0.14.0.dist-info/METADATA
pythonsdk-0.14.0.dist-info/WHEEL
pythonsdk-0.14.0.dist-info/entry_points.txt
pythonsdk-0.14.0.dist-info/top_level.txt
pythonsdk-0.14.0.dist-info/RECORD
