Metadata-Version: 2.1
Name: pythonsdk
Version: 0.14.0
Summary: Python Software Dev Kit
Author-email: lijok <lijok@pm.me>
License: MIT License
Project-URL: Homepage, https://github.com/lijok/python-sdk
Project-URL: Source Code, https://github.com/lijok/python-sdk
Project-URL: Documentation, https://github.com/lijok/python-sdk/docs
Project-URL: Changelog, https://github.com/lijok/python-sdk/blob/main/CHANGELOG.md
Project-URL: Bug Tracker, https://github.com/lijok/python-sdk/issues
Classifier: Development Status :: 1 - Planning
Classifier: Intended Audience :: Developers
Classifier: Intended Audience :: System Administrators
Classifier: License :: OSI Approved :: MIT License
Classifier: Natural Language :: English
Classifier: Operating System :: OS Independent
Classifier: Programming Language :: Python
Classifier: Programming Language :: Python :: 3
Classifier: Programming Language :: Python :: 3.10
Classifier: Programming Language :: Python :: 3.11
Classifier: Programming Language :: Python :: Implementation :: CPython
Requires-Python: >=3.10
License-File: LICENSE
Provides-Extra: aws
Requires-Dist: boto3 >=1.24 ; extra == 'aws'
Provides-Extra: cli
Requires-Dist: black >=22.10.0 ; extra == 'cli'
Requires-Dist: isort >=5.10.1 ; extra == 'cli'
Provides-Extra: dev
Requires-Dist: build >=0.8.0 ; extra == 'dev'
Requires-Dist: twine >=4.0.1 ; extra == 'dev'
Requires-Dist: hypothesis >=6.54.0 ; extra == 'dev'
Requires-Dist: pytest >=7.1.3 ; extra == 'dev'
Requires-Dist: pytest-asyncio >=0.19.0 ; extra == 'dev'
Requires-Dist: freezegun >=1.2.2 ; extra == 'dev'
Requires-Dist: boto3-stubs[cloudwatch,dynamodb,s3] >=1.26.127 ; extra == 'dev'
Requires-Dist: uvloop >=0.17.0 ; extra == 'dev'
Provides-Extra: lock-aws-dynamodb
Requires-Dist: boto3 >=1.24 ; extra == 'lock-aws-dynamodb'
Provides-Extra: lock-s3
Requires-Dist: boto3 >=1.24 ; extra == 'lock-s3'
Provides-Extra: metrics-aws-cloudwatch
Requires-Dist: boto3 >=1.24 ; extra == 'metrics-aws-cloudwatch'
Provides-Extra: testing
Requires-Dist: black >=22.10.0 ; extra == 'testing'
Requires-Dist: isort >=5.10.1 ; extra == 'testing'
Requires-Dist: mypy >=0.982 ; extra == 'testing'
